{
  "annotations": {
    "list": [
      {
        "builtIn": 1,
        "datasource": "-- Grafana --",
        "enable": true,
        "hide": true,
        "iconColor": "rgba(0, 211, 255, 1)",
        "limit": 100,
        "name": "Annotations & Alerts",
        "showIn": 0,
        "type": "dashboard"
      }
    ]
  },
  "editable": true,
  "gnetId": null,
  "graphTooltip": 0,
  "id": 55,
  "links": [],
  "panels": [
    {
      "collapsed": false,
      "gridPos": {
        "h": 7,
        "w": 24,
        "x": 0,
        "y": 0
      },
      "id": 19,
      "panels": [],
      "repeat": null,
      "title": "Histories",
      "type": "row"
    },
    {
      "aliasColors": {},
      "bars": false,
      "dashLength": 10,
      "dashes": false,
      "datasource": "InfluxDB - Graphite Connector",
      "editable": true,
      "error": false,
      "fill": 1,
      "grid": {},
      "gridPos": {
        "h": 7,
        "w": 12,
        "x": 0,
        "y": 1
      },
      "id": 9,
      "legend": {
        "alignAsTable": false,
        "avg": true,
        "current": false,
        "hideEmpty": false,
        "hideZero": false,
        "max": true,
        "min": true,
        "rightSide": true,
        "show": false,
        "total": false,
        "values": true
      },
      "lines": false,
      "linewidth": 2,
      "links": [],
      "nullPointMode": "connected",
      "percentage": false,
      "pointradius": 1,
      "points": true,
      "renderer": "flot",
      "seriesOverrides": [
        {
          "alias": "95th",
          "color": "#3F2B5B",
          "fill": 0,
          "lines": true,
          "points": false
        }
      ],
      "spaceLength": 10,
      "stack": false,
      "steppedLine": false,
      "targets": [
        {
          "alias": "mean",
          "dsType": "influxdb",
          "groupBy": [],
          "measurement": "denbi.galaxy.freiburg.api.history_contents.index",
          "orderByTime": "ASC",
          "policy": "default",
          "query": "SELECT \"mean\" FROM \"main_api_history_contents_index\" WHERE $timeFilter",
          "rawQuery": false,
          "refId": "A",
          "resultFormat": "time_series",
          "select": [
            [
              {
                "params": [
                  "mean"
                ],
                "type": "field"
              }
            ]
          ],
          "tags": []
        },
        {
          "alias": "95th",
          "dsType": "influxdb",
          "groupBy": [
            {
              "params": [
                "5m"
              ],
              "type": "time"
            },
            {
              "params": [
                "none"
              ],
              "type": "fill"
            }
          ],
          "measurement": "denbi.galaxy.freiburg.api.history_contents.index",
          "orderByTime": "ASC",
          "policy": "default",
          "query": "SELECT percentile(\"mean\", 95) FROM \"main_api_history_contents_index\" WHERE $timeFilter GROUP BY time(5m) fill(none)",
          "rawQuery": false,
          "refId": "B",
          "resultFormat": "time_series",
          "select": [
            [
              {
                "params": [
                  "mean"
                ],
                "type": "field"
              },
              {
                "params": [
                  95
                ],
                "type": "percentile"
              }
            ]
          ],
          "tags": []
        }
      ],
      "thresholds": [],
      "timeFrom": null,
      "timeShift": null,
      "title": "/api/histories/{history_id}/contents",
      "tooltip": {
        "msResolution": false,
        "shared": true,
        "sort": 0,
        "value_type": "cumulative"
      },
      "type": "graph",
      "xaxis": {
        "buckets": null,
        "mode": "time",
        "name": null,
        "show": true,
        "values": []
      },
      "yaxes": [
        {
          "format": "ms",
          "label": null,
          "logBase": 1,
          "max": null,
          "min": null,
          "show": true
        },
        {
          "format": "short",
          "label": null,
          "logBase": 1,
          "max": null,
          "min": null,
          "show": false
        }
      ]
    },
    {
      "aliasColors": {},
      "bars": false,
      "dashLength": 10,
      "dashes": false,
      "datasource": "InfluxDB - Graphite Connector",
      "editable": true,
      "error": false,
      "fill": 1,
      "grid": {},
      "gridPos": {
        "h": 7,
        "w": 12,
        "x": 12,
        "y": 1
      },
      "id": 12,
      "legend": {
        "alignAsTable": false,
        "avg": false,
        "current": false,
        "hideEmpty": false,
        "hideZero": false,
        "max": false,
        "min": false,
        "rightSide": false,
        "show": false,
        "total": false,
        "values": false
      },
      "lines": false,
      "linewidth": 2,
      "links": [],
      "nullPointMode": "connected",
      "percentage": false,
      "pointradius": 1,
      "points": true,
      "renderer": "flot",
      "seriesOverrides": [
        {
          "alias": "95th",
          "color": "#3F2B5B",
          "fill": 0,
          "lines": true,
          "points": false
        }
      ],
      "spaceLength": 10,
      "stack": false,
      "steppedLine": false,
      "targets": [
        {
          "alias": "mean",
          "dsType": "influxdb",
          "groupBy": [],
          "measurement": "denbi.galaxy.freiburg.api.histories.index",
          "orderByTime": "ASC",
          "policy": "default",
          "query": "SELECT \"mean\" FROM \"main_api_tools_index\" WHERE $timeFilter",
          "rawQuery": false,
          "refId": "A",
          "resultFormat": "time_series",
          "select": [
            [
              {
                "params": [
                  "mean"
                ],
                "type": "field"
              }
            ]
          ],
          "tags": []
        },
        {
          "alias": "95th",
          "dsType": "influxdb",
          "groupBy": [
            {
              "params": [
                "5m"
              ],
              "type": "time"
            },
            {
              "params": [
                "none"
              ],
              "type": "fill"
            }
          ],
          "measurement": "denbi.galaxy.freiburg.api.histories.index",
          "orderByTime": "ASC",
          "policy": "default",
          "query": "SELECT percentile(\"mean\", 95) FROM \"main_api_histories_show\" WHERE $timeFilter GROUP BY time(5m) fill(none)",
          "rawQuery": false,
          "refId": "B",
          "resultFormat": "time_series",
          "select": [
            [
              {
                "params": [
                  "mean"
                ],
                "type": "field"
              },
              {
                "params": [
                  95
                ],
                "type": "percentile"
              }
            ]
          ],
          "tags": []
        }
      ],
      "thresholds": [],
      "timeFrom": null,
      "timeShift": null,
      "title": "/api/histories/{history_id}",
      "tooltip": {
        "msResolution": false,
        "shared": true,
        "sort": 0,
        "value_type": "cumulative"
      },
      "type": "graph",
      "xaxis": {
        "buckets": null,
        "mode": "time",
        "name": null,
        "show": true,
        "values": []
      },
      "yaxes": [
        {
          "format": "ms",
          "label": null,
          "logBase": 1,
          "max": null,
          "min": null,
          "show": true
        },
        {
          "format": "short",
          "label": null,
          "logBase": 1,
          "max": null,
          "min": null,
          "show": true
        }
      ]
    },
    {
      "aliasColors": {},
      "bars": false,
      "dashLength": 10,
      "dashes": false,
      "datasource": "InfluxDB - Graphite Connector",
      "editable": true,
      "error": false,
      "fill": 1,
      "grid": {},
      "gridPos": {
        "h": 7,
        "w": 12,
        "x": 0,
        "y": 8
      },
      "id": 15,
      "legend": {
        "alignAsTable": false,
        "avg": false,
        "current": false,
        "hideEmpty": false,
        "hideZero": false,
        "max": false,
        "min": false,
        "rightSide": false,
        "show": false,
        "total": false,
        "values": false
      },
      "lines": false,
      "linewidth": 2,
      "links": [],
      "nullPointMode": "connected",
      "percentage": false,
      "pointradius": 1,
      "points": true,
      "renderer": "flot",
      "seriesOverrides": [
        {
          "alias": "95th",
          "color": "#3F2B5B",
          "fill": 0,
          "lines": true,
          "points": false
        }
      ],
      "spaceLength": 10,
      "stack": false,
      "steppedLine": false,
      "targets": [
        {
          "alias": "mean",
          "dsType": "influxdb",
          "groupBy": [],
          "measurement": "denbi.galaxy.freiburg.api.history_contents.show",
          "orderByTime": "ASC",
          "policy": "default",
          "query": "SELECT \"mean\" FROM \"main_api_history_contents_show\" WHERE $timeFilter",
          "rawQuery": false,
          "refId": "A",
          "resultFormat": "time_series",
          "select": [
            [
              {
                "params": [
                  "mean"
                ],
                "type": "field"
              }
            ]
          ],
          "tags": []
        },
        {
          "alias": "95th",
          "dsType": "influxdb",
          "groupBy": [
            {
              "params": [
                "5m"
              ],
              "type": "time"
            },
            {
              "params": [
                "none"
              ],
              "type": "fill"
            }
          ],
          "measurement": "denbi.galaxy.freiburg.api.history_contents.show",
          "orderByTime": "ASC",
          "policy": "default",
          "query": "SELECT percentile(\"mean\", 95) FROM \"main_api_history_contents_show\" WHERE $timeFilter GROUP BY time(5m) fill(none)",
          "rawQuery": false,
          "refId": "B",
          "resultFormat": "time_series",
          "select": [
            [
              {
                "params": [
                  "mean"
                ],
                "type": "field"
              },
              {
                "params": [
                  95
                ],
                "type": "percentile"
              }
            ]
          ],
          "tags": []
        }
      ],
      "thresholds": [],
      "timeFrom": null,
      "timeShift": null,
      "title": "/api/histories/{history_id}/contents/{id}",
      "tooltip": {
        "msResolution": false,
        "shared": true,
        "sort": 0,
        "value_type": "cumulative"
      },
      "type": "graph",
      "xaxis": {
        "buckets": null,
        "mode": "time",
        "name": null,
        "show": true,
        "values": []
      },
      "yaxes": [
        {
          "format": "ms",
          "label": null,
          "logBase": 1,
          "max": null,
          "min": null,
          "show": true
        },
        {
          "format": "short",
          "label": null,
          "logBase": 1,
          "max": null,
          "min": null,
          "show": true
        }
      ]
    },
    {
      "aliasColors": {},
      "bars": false,
      "dashLength": 10,
      "dashes": false,
      "datasource": "InfluxDB - Graphite Connector",
      "editable": true,
      "error": false,
      "fill": 1,
      "grid": {},
      "gridPos": {
        "h": 7,
        "w": 12,
        "x": 12,
        "y": 8
      },
      "id": 16,
      "legend": {
        "alignAsTable": false,
        "avg": false,
        "current": false,
        "hideEmpty": false,
        "hideZero": false,
        "max": false,
        "min": false,
        "rightSide": false,
        "show": false,
        "total": false,
        "values": false
      },
      "lines": false,
      "linewidth": 2,
      "links": [],
      "nullPointMode": "connected",
      "percentage": false,
      "pointradius": 1,
      "points": true,
      "renderer": "flot",
      "seriesOverrides": [
        {
          "alias": "95th",
          "color": "#3F2B5B",
          "fill": 0,
          "lines": true,
          "points": false
        }
      ],
      "spaceLength": 10,
      "stack": false,
      "steppedLine": false,
      "targets": [
        {
          "alias": "mean",
          "dsType": "influxdb",
          "groupBy": [],
          "measurement": "denbi.galaxy.freiburg.api.history_contents.update",
          "orderByTime": "ASC",
          "policy": "default",
          "query": "SELECT \"mean\" FROM \"main_api_history_contents_update\" WHERE $timeFilter",
          "rawQuery": false,
          "refId": "A",
          "resultFormat": "time_series",
          "select": [
            [
              {
                "params": [
                  "mean"
                ],
                "type": "field"
              }
            ]
          ],
          "tags": []
        },
        {
          "alias": "95th",
          "dsType": "influxdb",
          "groupBy": [
            {
              "params": [
                "5m"
              ],
              "type": "time"
            },
            {
              "params": [
                "none"
              ],
              "type": "fill"
            }
          ],
          "measurement": "denbi.galaxy.freiburg.api.history_contents.update",
          "orderByTime": "ASC",
          "policy": "default",
          "query": "SELECT percentile(\"mean\", 95) FROM \"main_api_history_contents_update\" WHERE $timeFilter GROUP BY time(5m) fill(none)",
          "rawQuery": false,
          "refId": "B",
          "resultFormat": "time_series",
          "select": [
            [
              {
                "params": [
                  "mean"
                ],
                "type": "field"
              },
              {
                "params": [
                  95
                ],
                "type": "percentile"
              }
            ]
          ],
          "tags": []
        }
      ],
      "thresholds": [],
      "timeFrom": null,
      "timeShift": null,
      "title": "PUT /api/histories/{history_id}/contents/datasets/{id}",
      "tooltip": {
        "msResolution": false,
        "shared": true,
        "sort": 0,
        "value_type": "cumulative"
      },
      "type": "graph",
      "xaxis": {
        "buckets": null,
        "mode": "time",
        "name": null,
        "show": true,
        "values": []
      },
      "yaxes": [
        {
          "format": "ms",
          "label": null,
          "logBase": 1,
          "max": null,
          "min": null,
          "show": true
        },
        {
          "format": "short",
          "label": null,
          "logBase": 1,
          "max": null,
          "min": null,
          "show": true
        }
      ]
    },
    {
      "aliasColors": {},
      "bars": false,
      "dashLength": 10,
      "dashes": false,
      "datasource": "InfluxDB - Graphite Connector",
      "editable": true,
      "error": false,
      "fill": 1,
      "grid": {},
      "gridPos": {
        "h": 7,
        "w": 12,
        "x": 0,
        "y": 15
      },
      "id": 13,
      "legend": {
        "alignAsTable": false,
        "avg": false,
        "current": false,
        "hideEmpty": false,
        "hideZero": false,
        "max": false,
        "min": false,
        "rightSide": false,
        "show": false,
        "total": false,
        "values": false
      },
      "lines": false,
      "linewidth": 2,
      "links": [],
      "nullPointMode": "connected",
      "percentage": false,
      "pointradius": 1,
      "points": true,
      "renderer": "flot",
      "seriesOverrides": [
        {
          "alias": "95th",
          "color": "#3F2B5B",
          "fill": 0,
          "lines": true,
          "points": false
        }
      ],
      "spaceLength": 10,
      "stack": false,
      "steppedLine": false,
      "targets": [
        {
          "alias": "mean",
          "dsType": "influxdb",
          "groupBy": [],
          "measurement": "denbi.galaxy.freiburg.api.histories.index",
          "orderByTime": "ASC",
          "policy": "default",
          "query": "SELECT \"mean\" FROM \"main_api_tools_index\" WHERE $timeFilter",
          "rawQuery": false,
          "refId": "A",
          "resultFormat": "time_series",
          "select": [
            [
              {
                "params": [
                  "mean"
                ],
                "type": "field"
              }
            ]
          ],
          "tags": []
        },
        {
          "alias": "95th",
          "dsType": "influxdb",
          "groupBy": [
            {
              "params": [
                "5m"
              ],
              "type": "time"
            },
            {
              "params": [
                "none"
              ],
              "type": "fill"
            }
          ],
          "measurement": "denbi.galaxy.freiburg.api.histories.index",
          "orderByTime": "ASC",
          "policy": "default",
          "query": "SELECT percentile(\"mean\", 95) FROM \"main_api_histories_index\" WHERE $timeFilter GROUP BY time(5m) fill(none)",
          "rawQuery": false,
          "refId": "B",
          "resultFormat": "time_series",
          "select": [
            [
              {
                "params": [
                  "mean"
                ],
                "type": "field"
              },
              {
                "params": [
                  95
                ],
                "type": "percentile"
              }
            ]
          ],
          "tags": []
        }
      ],
      "thresholds": [],
      "timeFrom": null,
      "timeShift": null,
      "title": "/api/histories",
      "tooltip": {
        "msResolution": false,
        "shared": true,
        "sort": 0,
        "value_type": "cumulative"
      },
      "type": "graph",
      "xaxis": {
        "buckets": null,
        "mode": "time",
        "name": null,
        "show": true,
        "values": []
      },
      "yaxes": [
        {
          "format": "ms",
          "label": null,
          "logBase": 1,
          "max": null,
          "min": null,
          "show": true
        },
        {
          "format": "short",
          "label": null,
          "logBase": 1,
          "max": null,
          "min": null,
          "show": true
        }
      ]
    },
    {
      "aliasColors": {},
      "bars": false,
      "dashLength": 10,
      "dashes": false,
      "datasource": "InfluxDB - Graphite Connector",
      "editable": true,
      "error": false,
      "fill": 1,
      "grid": {},
      "gridPos": {
        "h": 7,
        "w": 12,
        "x": 12,
        "y": 15
      },
      "id": 17,
      "legend": {
        "alignAsTable": false,
        "avg": false,
        "current": false,
        "hideEmpty": false,
        "hideZero": false,
        "max": false,
        "min": false,
        "rightSide": false,
        "show": false,
        "total": false,
        "values": false
      },
      "lines": false,
      "linewidth": 2,
      "links": [],
      "nullPointMode": "connected",
      "percentage": false,
      "pointradius": 1,
      "points": true,
      "renderer": "flot",
      "seriesOverrides": [
        {
          "alias": "95th",
          "color": "#3F2B5B",
          "fill": 0,
          "lines": true,
          "points": false
        }
      ],
      "spaceLength": 10,
      "stack": false,
      "steppedLine": false,
      "targets": [
        {
          "alias": "mean",
          "dsType": "influxdb",
          "groupBy": [],
          "measurement": "denbi.galaxy.freiburg.web.history.list",
          "orderByTime": "ASC",
          "policy": "default",
          "query": "SELECT \"mean\" FROM \"main_web_history_list\" WHERE $timeFilter",
          "rawQuery": false,
          "refId": "A",
          "resultFormat": "time_series",
          "select": [
            [
              {
                "params": [
                  "mean"
                ],
                "type": "field"
              }
            ]
          ],
          "tags": []
        },
        {
          "alias": "95th",
          "dsType": "influxdb",
          "groupBy": [
            {
              "params": [
                "5m"
              ],
              "type": "time"
            },
            {
              "params": [
                "none"
              ],
              "type": "fill"
            }
          ],
          "measurement": "denbi.galaxy.freiburg.web.history.list",
          "orderByTime": "ASC",
          "policy": "default",
          "query": "SELECT percentile(\"mean\", 95) FROM \"main_web_history_list\" WHERE $timeFilter GROUP BY time(5m) fill(none)",
          "rawQuery": false,
          "refId": "B",
          "resultFormat": "time_series",
          "select": [
            [
              {
                "params": [
                  "mean"
                ],
                "type": "field"
              },
              {
                "params": [
                  95
                ],
                "type": "percentile"
              }
            ]
          ],
          "tags": []
        }
      ],
      "thresholds": [],
      "timeFrom": null,
      "timeShift": null,
      "title": "histories list operations",
      "tooltip": {
        "msResolution": false,
        "shared": true,
        "sort": 0,
        "value_type": "cumulative"
      },
      "type": "graph",
      "xaxis": {
        "buckets": null,
        "mode": "time",
        "name": null,
        "show": true,
        "values": []
      },
      "yaxes": [
        {
          "format": "ms",
          "label": null,
          "logBase": 1,
          "max": null,
          "min": null,
          "show": true
        },
        {
          "format": "short",
          "label": null,
          "logBase": 1,
          "max": null,
          "min": null,
          "show": true
        }
      ]
    },
    {
      "aliasColors": {},
      "bars": false,
      "dashLength": 10,
      "dashes": false,
      "datasource": "InfluxDB - Graphite Connector",
      "editable": true,
      "error": false,
      "fill": 1,
      "grid": {},
      "gridPos": {
        "h": 7,
        "w": 12,
        "x": 0,
        "y": 22
      },
      "id": 18,
      "legend": {
        "alignAsTable": false,
        "avg": false,
        "current": false,
        "hideEmpty": false,
        "hideZero": false,
        "max": false,
        "min": false,
        "rightSide": false,
        "show": false,
        "total": false,
        "values": false
      },
      "lines": false,
      "linewidth": 2,
      "links": [],
      "nullPointMode": "connected",
      "percentage": false,
      "pointradius": 1,
      "points": true,
      "renderer": "flot",
      "seriesOverrides": [
        {
          "alias": "95th",
          "color": "#3F2B5B",
          "fill": 0,
          "lines": true,
          "points": false
        },
        {
          "alias": "count",
          "fill": 0,
          "lines": true,
          "points": false
        }
      ],
      "spaceLength": 10,
      "stack": false,
      "steppedLine": false,
      "targets": [
        {
          "alias": "mean",
          "dsType": "influxdb",
          "groupBy": [],
          "measurement": "denbi.galaxy.freiburg.api.history_contents.index",
          "orderByTime": "ASC",
          "policy": "default",
          "query": "SELECT \"mean\" FROM \"main_api_history_contents_index\" WHERE $timeFilter",
          "rawQuery": false,
          "refId": "A",
          "resultFormat": "time_series",
          "select": [
            [
              {
                "params": [
                  "mean"
                ],
                "type": "field"
              }
            ]
          ],
          "tags": []
        },
        {
          "alias": "95th",
          "dsType": "influxdb",
          "groupBy": [
            {
              "params": [
                "5m"
              ],
              "type": "time"
            },
            {
              "params": [
                "none"
              ],
              "type": "fill"
            }
          ],
          "measurement": "denbi.galaxy.freiburg.api.history_contents.index",
          "orderByTime": "ASC",
          "policy": "default",
          "query": "SELECT percentile(\"mean\", 95) FROM \"main_api_history_contents_index\" WHERE $timeFilter GROUP BY time(5m) fill(none)",
          "rawQuery": false,
          "refId": "B",
          "resultFormat": "time_series",
          "select": [
            [
              {
                "params": [
                  "mean"
                ],
                "type": "field"
              },
              {
                "params": [
                  95
                ],
                "type": "percentile"
              }
            ]
          ],
          "tags": []
        }
      ],
      "thresholds": [],
      "timeFrom": null,
      "timeShift": null,
      "title": "/api/histories/{history_id}/contents",
      "tooltip": {
        "msResolution": false,
        "shared": true,
        "sort": 0,
        "value_type": "cumulative"
      },
      "type": "graph",
      "xaxis": {
        "buckets": null,
        "mode": "time",
        "name": null,
        "show": false,
        "values": []
      },
      "yaxes": [
        {
          "format": "ms",
          "label": null,
          "logBase": 1,
          "max": null,
          "min": null,
          "show": true
        },
        {
          "format": "short",
          "label": null,
          "logBase": 1,
          "max": null,
          "min": null,
          "show": true
        }
      ]
    }
  ],
  "refresh": "5m",
  "schemaVersion": 16,
  "style": "dark",
  "tags": [
    "API"
  ],
  "templating": {
    "list": []
  },
  "time": {
    "from": "now-6h",
    "to": "now"
  },
  "timepicker": {
    "refresh_intervals": [
      "5s",
      "10s",
      "30s",
      "1m",
      "5m",
      "15m",
      "30m",
      "1h",
      "2h",
      "1d"
    ],
    "time_options": [
      "5m",
      "15m",
      "1h",
      "6h",
      "12h",
      "24h",
      "2d",
      "7d",
      "30d"
    ]
  },
  "timezone": "browser",
  "title": "Histories",
  "uid": "000000055",
  "version": 3
}
